pysweep/__init__.py
pysweep/__main__.py
pysweep/minefield.py
pysweep/sweeper.py
pysweep/tile.py
pysweep-0.1.0.dist-info/METADATA
pysweep-0.1.0.dist-info/WHEEL
pysweep-0.1.0.dist-info/entry_points.txt
pysweep-0.1.0.dist-info/top_level.txt
pysweep-0.1.0.dist-info/RECORD
